clt_queued_run_coordinator/__init__.py
clt_queued_run_coordinator/coordinator.py
dagster_clt_queued_run_coordinator-0.1.0.dist-info/licenses/LICENSE
dagster_clt_queued_run_coordinator-0.1.0.dist-info/METADATA
dagster_clt_queued_run_coordinator-0.1.0.dist-info/WHEEL
dagster_clt_queued_run_coordinator-0.1.0.dist-info/top_level.txt
dagster_clt_queued_run_coordinator-0.1.0.dist-info/RECORD
