Metadata-Version: 2.4
Name: dagster-clt-queued-run-coordinator
Version: 0.1.0
Summary: Code Location Tagging (CLT) QueuedRunCoordinator – a custom Dagster run coordinator that automatically injects code-location tags before queuing.
Author-email: Jungsub Shin <supsup5642@gmail.com>
License: MIT
Classifier: Programming Language :: Python :: 3
Classifier: Programming Language :: Python :: 3 :: Only
Classifier: License :: OSI Approved :: MIT License
Requires-Python: >=3.9
License-File: LICENSE
Requires-Dist: dagster>=1.10.0
Dynamic: license-file
